gdgen/__init__.py
gdgen/__main__.py
gdgen/builders.py
gdgen/cli.py
gdgen/common.py
gdgen/gdmodule.py
gdgen/gdtypes.py
gdgen/messages.py
gdgen/methods.py
gdgen/module.py
gdgen/vcs.py
gdgen/configs/README.md
gdgen/configs/default.json
gdgen/configs/minimal.json
gdgen/configs/user/.gitkeep
gdgen/templates/licenses/MIT.txt
gdgen/templates/vcs/git/.gitattributes
gdgen/templates/vcs/git/.gitignore
gdgen/tests/test_gdmodule.py
gdgen/tests/configs/sample.json
gdgen-1.0a0.dist-info/LICENSE.md
gdgen-1.0a0.dist-info/METADATA
gdgen-1.0a0.dist-info/WHEEL
gdgen-1.0a0.dist-info/entry_points.txt
gdgen-1.0a0.dist-info/top_level.txt
gdgen-1.0a0.dist-info/RECORD
