Metadata-Version: 2.1
Name: gdgen
Version: 1.0a0
Summary: Code generator for Godot Engine
Home-page: https://github.com/Xrayez/gdgen
Author: Andrii Doroshenko (Xrayez)
Author-email: xrayez@gmail.com
License: MIT
Platform: UNKNOWN
Classifier: Development Status :: 3 - Alpha
Classifier: Programming Language :: Python :: 3
Classifier: Intended Audience :: Developers
Classifier: Topic :: Software Development :: Code Generators
Classifier: License :: OSI Approved :: MIT License
Classifier: Operating System :: OS Independent
Requires-Python: >=3.6
